vemomoto_core/concurrent/__init__.py
vemomoto_core/concurrent/concurrent_futures_ext.py
vemomoto_core/concurrent/nicepar.py
vemomoto_core/concurrent/sharedmem_ext.py
vemomoto_core_concurrent-0.9.0a1.dist-info/LICENSE
vemomoto_core_concurrent-0.9.0a1.dist-info/METADATA
vemomoto_core_concurrent-0.9.0a1.dist-info/WHEEL
vemomoto_core_concurrent-0.9.0a1.dist-info/top_level.txt
vemomoto_core_concurrent-0.9.0a1.dist-info/RECORD
