Metadata-Version: 2.1
Name: vemomoto-core-concurrent
Version: 0.9.0a1
Summary: Methods to ease parallelization of code
Home-page: https://github.com/vemomoto/vemomoto
Author: Samuel M. Fischer
License: LGPLv3
Project-URL: Bug Tracker, https://github.com/vemomoto/vemomoto/issues
Project-URL: Documentation, https://vemomoto.github.io/vemomoto_core/vemomoto_core.concurrent
Project-URL: Source Code, https://github.com/vemomoto/vemomoto/tree/master/vemomoto_core/vemomoto_core_concurrent
Keywords: parallel,shared memory,multiprocessing,concurrency
Platform: UNKNOWN
Classifier: License :: OSI Approved :: GNU Lesser General Public License v3 (LGPLv3)
Classifier: Development Status :: 3 - Alpha
Classifier: Intended Audience :: Developers
Requires-Python: >=3.6
Requires-Dist: numpy
Requires-Dist: sharedmem
